{
  "rooms": [ 
    { 
    "room": "G01", 
    "name": "Foyer", 
    "lecturer": "", 
    "floor": "ground", 
    "type": "", 
    "x": 124, 
    "y": 563, 
    "keywords": ["enterence"] 
  },
    {
      "room": "G02",
      "name": "Office",
      "lecturer": "",
      "floor": "ground",
      "type": "room",
      "x": 225,
      "y": 408,
      "keywords": ["information", "enterence", "help"]
    },
    {
      "room": "Lab0",
      "name": "Computer Suite",
      "lecturer": "",
      "floor": "ground",
      "type": "lab",
      "x": 380,
      "y": 350,
      "keywords": ["computers", "it", "lab"]
    },
    {
      "room": "CG03",
      "name": "Space",
      "lecturer": "",
      "floor": "ground",
      "type": "lab",
      "x": 576,
      "y": 406,
      "keywords": ["group space", "it", "lab"]
    },
    {
      "room": "Lab1",
      "name": "Computer Suite",
      "lecturer": "",
      "floor": "ground",
      "type": "lab",
      "x": 764,
      "y": 348,
      "keywords": ["computers", "it", "lab"]
    },
    {
      "room": "G05",
      "name": "Office",
      "lecturer": "",
      "floor": "ground",
      "type": "lab",
      "x": 957,
      "y": 406,
      "keywords": ["office", "it", "lab", "meeting"]
    },
    {
      "room": "Lab2",
      "name": "Computer Suite",
      "lecturer": "",
      "floor": "ground",
      "type": "lab",
      "x": 1147,
      "y": 359,
      "keywords": ["computers", "it", "lab"]
    },
    {
      "room": "G07",
      "name": "Office",
      "lecturer": "",
      "floor": "ground",
      "type": "lab",
      "x": 1311,
      "y": 418,
      "keywords": ["office", "it", "help"]
    },
    {
      "room": "G08",
      "name": "Seminar Room",
      "lecturer": "",
      "floor": "ground",
      "type": "room",
      "x": 1373,
      "y": 557,
      "keywords": ["meeting", "lecture", "seminar"]
    },
    {
      "name": "WC - Shared",
      "lecturer": "",
      "floor": "ground",
      "type": "facility",
      "x": 757,
      "y": 727,
      "keywords": ["toilet", "bathroom", "wc"]
    },
    {
      "room": "Lab3",
      "floor": "ground",
      "type": "lab",
      "x": 1125,
      "y": 782,
      "keywords": ["computers", "it", "lab"]
    },
    {
      "room": "CG16",
      "name": "Circulation Space",
      "floor": "ground",
      "type": "facility",
      "x": 615,
      "y": 661,
      "keywords": ["computers", "it", "group space"]
    },
    {
      "room": "G16 Lecture Theatre",
      "name": "Wolfston Theatre",
      "lecturer": "",
      "floor": "ground",
      "type": "lab",
      "x": 768,
      "y": 874,
      "keywords": ["meeting", "lecture", "seminar"]
    },
    {
      "room": "G21",
      "name": "Computer Suite",
      "lecturer": "",
      "floor": "ground",
      "type": "lab",
      "x": 430,
      "y": 785,
      "keywords": ["computers", "it", "group space"]
    },
    {
      "name": "Lift",
      "floor": "ground",
      "type": "facility",
      "x": 507,
      "y": 627,
      "keywords": ["lift", "elevator"]
    },
    {
      "name": "Stairs",
      "floor": "ground",
      "type": "facility",
      "x": 266,
      "y": 557,
      "keywords": ["stairs", "staircase"]
    },
    {
      "name": "Stairs",
      "floor": "ground",
      "type": "facility",
      "x": 1013,
      "y": 576,
      "keywords": ["stairs", "staircase"]
    },
    {
      "name": "Kitchen",
      "floor": "ground",
      "type": "facility",
      "x": 548,
      "y": 559,
      "keywords": ["kitchen", "food", "cooking"]
    },
    {
      "name": "Cleaners Store",
      "floor": "ground",
      "type": "facility",
      "x": 359,
      "y": 559,
      "keywords": ["cleaning", "supplies"]
    },
    {
      "name": "WC - Ladies",
      "floor": "ground",
      "type": "facility",
      "x": 725,
      "y": 555,
      "keywords": ["toilet", "bathroom", "wc"]
    },
    {
      "name": "WC - Gents",
      "floor": "ground",
      "type": "facility",
      "x": 873,
      "y": 557,
      "keywords": ["toilet", "bathroom", "wc"]
    },
    {
      "name": "Accessible WC",
      "floor": "ground",
      "type": "facility",
      "x": 630,
      "y": 576,
      "keywords": ["toilet", "bathroom", "accessible", "wc"]
    }
  ]
}